gen_odoo_readme-1.3.58.data/data/mypackage/gen_addon_readme.template
tools/__init__.py
tools/__main__.py
tools/gen_addon_readme.template
tools/gen_readme.py
tools/manifest.py
gen_odoo_readme-1.3.58.dist-info/LICENSE
gen_odoo_readme-1.3.58.dist-info/METADATA
gen_odoo_readme-1.3.58.dist-info/WHEEL
gen_odoo_readme-1.3.58.dist-info/entry_points.txt
gen_odoo_readme-1.3.58.dist-info/top_level.txt
gen_odoo_readme-1.3.58.dist-info/RECORD
