Metadata-Version: 2.1
Name: gen-odoo-readme
Version: 1.3.58
Summary: Tool to create README.rst files for Odoo
Home-page: https://github.com/jobiols/gen-readme
Author: Jorge E. Obiols
Author-email: jorge.obiols@gmail.com
Keywords: odoo documentation readme rst
Classifier: Development Status :: 5 - Production/Stable
Classifier: Intended Audience :: Developers
Classifier: License :: OSI Approved :: MIT License
Classifier: Programming Language :: Python :: 3.8
Classifier: Operating System :: OS Independent
Classifier: Topic :: Software Development :: Documentation
Requires-Python: >=3.8
License-File: LICENSE
Requires-Dist: click ==8.1.7
Requires-Dist: jinja2 ==3.1.4
Requires-Dist: docutils >=0.21.0
Requires-Dist: Pygments ==2.18.0
Requires-Dist: PyYAML ==6.0.2
